circuit_breaker_box/__init__.py
circuit_breaker_box/circuit_breaker_base.py
circuit_breaker_box/circuit_breaker_in_memory.py
circuit_breaker_box/circuit_breaker_redis.py
circuit_breaker_box/common_types.py
circuit_breaker_box/errors.py
circuit_breaker_box/py.typed
circuit_breaker_box/retrier.py
circuit_breaker_box-0.3.7.dist-info/METADATA
circuit_breaker_box-0.3.7.dist-info/WHEEL
circuit_breaker_box-0.3.7.dist-info/RECORD
