Metadata-Version: 2.4
Name: circuit-breaker-box
Version: 0.3.7
Summary: Implementations of the Circuit Breaker
Project-URL: Repository, https://github.com/community-of-python/circuit-breaker-box
Project-URL: Issues, https://github.com/community-of-python/circuit-breaker-box/issues
Project-URL: Changelogs, https://github.com/community-of-python/circuit-breaker-box/releases
Author: community-of-python
Keywords: python
Classifier: Programming Language :: Python :: 3.10
Classifier: Programming Language :: Python :: 3.11
Classifier: Programming Language :: Python :: 3.12
Classifier: Programming Language :: Python :: 3.13
Classifier: Typing :: Typed
Requires-Python: <4,>=3.10
Requires-Dist: cachetools
Requires-Dist: httpx
Requires-Dist: tenacity
Provides-Extra: redis
Requires-Dist: redis; extra == 'redis'
